naverplaceapi/__init__.py
naverplaceapi/mixin/__init__.py
naverplaceapi/mixin/_query.py
naverplaceapi/mixin/address.py
naverplaceapi/mixin/announce.py
naverplaceapi/mixin/booking.py
naverplaceapi/mixin/broadcast.py
naverplaceapi/mixin/category.py
naverplaceapi/mixin/geocode.py
naverplaceapi/mixin/menu.py
naverplaceapi/mixin/place.py
naverplaceapi/mixin/promotions.py
naverplaceapi/mixin/query/__init__.py
naverplaceapi/mixin/query/get_announcements.py
naverplaceapi/mixin/query/get_booking_items.py
naverplaceapi/mixin/query/get_fsas_reviews.py
naverplaceapi/mixin/query/get_popular_menus.py
naverplaceapi/mixin/query/get_promotions.py
naverplaceapi/mixin/query/get_restaurant.py
naverplaceapi/mixin/query/get_restaurants.py
naverplaceapi/mixin/query/get_ugc_reviews.py
naverplaceapi/mixin/query/get_visitor_review_photos_in_visitor_review_tab.py
naverplaceapi/mixin/query/get_visitor_review_stats.py
naverplaceapi/mixin/query/get_visitor_review_theme_lists.py
naverplaceapi/mixin/query/get_visitor_reviews.py
naverplaceapi/mixin/review.py
naverplaceapi/mixin/search.py
naverplaceapi/mixin/utils.py
naverplaceapi/tor_manager.py
naverplaceapi-0.1.46.dist-info/METADATA
naverplaceapi-0.1.46.dist-info/WHEEL
naverplaceapi-0.1.46.dist-info/RECORD
